forex_convert/__init__.py
forex_convert/currency_rates.py
forex_convert/module.py
forex_convert-0.0.5.dist-info/METADATA
forex_convert-0.0.5.dist-info/WHEEL
forex_convert-0.0.5.dist-info/licenses/LICENSE.txt
forex_convert-0.0.5.dist-info/RECORD
